kubernetes_lite/__init__.py
kubernetes_lite/_version.py
kubernetes_lite/errors.py
kubernetes_lite/go.mod
kubernetes_lite/go.sum
kubernetes_lite/serialization.py
kubernetes_lite/client/__init__.py
kubernetes_lite/client/client.py
kubernetes_lite/client/discovery.py
kubernetes_lite/client/resource.py
kubernetes_lite/client/sanitization.py
kubernetes_lite/client/watch.py
kubernetes_lite/envtest/__init__.py
kubernetes_lite/envtest/envtest.py
kubernetes_lite/envtest/pytest.py
kubernetes_lite/go_wrapper/go.mod
kubernetes_lite/go_wrapper/go.sum
kubernetes_lite/go_wrapper/internal/error.go
kubernetes_lite/go_wrapper/internal/kubeconfig.go
kubernetes_lite/go_wrapper/internal/serialization.go
kubernetes_lite/go_wrapper/pkg/client/client.go
kubernetes_lite/go_wrapper/pkg/client/namespaced_resource.go
kubernetes_lite/go_wrapper/pkg/client/resource.go
kubernetes_lite/go_wrapper/pkg/client/watch.go
kubernetes_lite/go_wrapper/pkg/client_run/main.go
kubernetes_lite/go_wrapper/pkg/envtest/server/run.go
kubernetes_lite/go_wrapper/pkg/envtest/setup/run.go
kubernetes_lite/go_wrapper/pkg/envtest/setup/stream.go
kubernetes_lite/go_wrapper/pkg/envtest/setup/vendored_main.go
kubernetes_lite/licenses/PYTHON_LICENSES
kubernetes_lite/licenses/python
kubernetes_lite/licenses/go/LICENSE
kubernetes_lite/licenses/go/crypto/internal/boring/LICENSE
kubernetes_lite/licenses/go/github.com/beorn7/perks/quantile/LICENSE
kubernetes_lite/licenses/go/github.com/cespare/xxhash/v2/LICENSE.txt
kubernetes_lite/licenses/go/github.com/davecgh/go-spew/spew/LICENSE
kubernetes_lite/licenses/go/github.com/emicklei/go-restful/v3/LICENSE
kubernetes_lite/licenses/go/github.com/evanphx/json-patch/v5/LICENSE
kubernetes_lite/licenses/go/github.com/fsnotify/fsnotify/LICENSE
kubernetes_lite/licenses/go/github.com/fxamacker/cbor/v2/LICENSE
kubernetes_lite/licenses/go/github.com/go-logr/logr/LICENSE
kubernetes_lite/licenses/go/github.com/go-logr/zapr/LICENSE
kubernetes_lite-0.1.0.dist-info/licenses/LICENSE
kubernetes_lite-0.1.0.dist-info/METADATA
kubernetes_lite-0.1.0.dist-info/WHEEL
kubernetes_lite-0.1.0.dist-info/top_level.txt
kubernetes_lite-0.1.0.dist-info/RECORD
