Metadata-Version: 2.4
Name: kubernetes_lite
Version: 0.1.0
Summary: Kubernetes Lite is a "liteweight" wrapper around various golang Kubernetes libraries using gopy
License-Expression: Apache-2.0
Classifier: Programming Language :: Go
Classifier: Development Status :: 4 - Beta
Requires-Python: >=3.11
License-File: LICENSE
Requires-Dist: orjson~=3.10.13
Provides-Extra: gen
Requires-Dist: pybindgen; extra == "gen"
Requires-Dist: typer; extra == "gen"
Requires-Dist: pip-licenses; extra == "gen"
Provides-Extra: test
Requires-Dist: pytest~=8.3.4; extra == "test"
Requires-Dist: pytest-cov>=2.10.1; extra == "test"
Requires-Dist: deepdiff~=7.0.1; extra == "test"
Requires-Dist: kubernetes~=30.1.0; extra == "test"
Provides-Extra: perf
Requires-Dist: typer; extra == "perf"
Requires-Dist: kubernetes~=30.1.0; extra == "perf"
Requires-Dist: kr8s; extra == "perf"
Requires-Dist: psutil; extra == "perf"
Provides-Extra: docs
Requires-Dist: mkdocs; extra == "docs"
Requires-Dist: mkdocs-material; extra == "docs"
Requires-Dist: mkdocstrings; extra == "docs"
Requires-Dist: mkdocstrings-python; extra == "docs"
Requires-Dist: mkdocs-autorefs; extra == "docs"
Dynamic: license-file
